app/__init__.py
app/app.py
my_flask_app_pratik_12345-0.5.0.dist-info/METADATA
my_flask_app_pratik_12345-0.5.0.dist-info/WHEEL
my_flask_app_pratik_12345-0.5.0.dist-info/top_level.txt
my_flask_app_pratik_12345-0.5.0.dist-info/RECORD
